morpheus/__init__.py
morpheus/game_config.py
morpheus/game_interface.py
morpheus/game_move.py
morpheus/game_moves.py
morpheus/game_object.py
morpheus/game_process.py
morpheus/game_processes.py
morpheus/game_rule.py
morpheus/game_rules.py
morpheus/game_state.py
morpheus/game_wrapper.py
morpheus/message.py
morpheus/module_loader.py
morpheus_game_framework-0.8.5.dist-info/METADATA
morpheus_game_framework-0.8.5.dist-info/RECORD
morpheus_game_framework-0.8.5.dist-info/WHEEL
morpheus_game_framework-0.8.5.dist-info/top_level.txt
tests/__init__.py
tests/test_game_config.py
tests/test_game_moves.py
tests/test_game_object.py
tests/test_parsing_json.py
