Metadata-Version: 2.1
Name: morpheus-game-framework
Version: 0.8.5
Summary: Framework for developing games for the Morpheus platform
Home-page: UNKNOWN
Author: morpheus team
Author-email: mihael@morpheuszone.com
License: MIT
Platform: UNKNOWN
Classifier: Development Status :: 3 - Alpha
Classifier: Programming Language :: Python :: 3
Classifier: License :: OSI Approved :: MIT License
Classifier: Operating System :: OS Independent
Requires-Dist: pyyaml
